bcra_connector/__about__.py
bcra_connector/__init__.py
bcra_connector/_version.py
bcra_connector/bcra_connector.py
bcra_connector/rate_limiter.py
bcra_connector/timeout_config.py
bcra_connector/central_deudores/__init__.py
bcra_connector/central_deudores/central_deudores.py
bcra_connector/cheques/__init__.py
bcra_connector/cheques/cheques.py
bcra_connector/estadisticas_cambiarias/__init__.py
bcra_connector/estadisticas_cambiarias/estadisticas_cambiarias.py
bcra_connector/principales_variables/__init__.py
bcra_connector/principales_variables/principales_variables.py
bcra_connector-0.9.0.dist-info/METADATA
bcra_connector-0.9.0.dist-info/WHEEL
bcra_connector-0.9.0.dist-info/licenses/LICENSE
bcra_connector-0.9.0.dist-info/RECORD
