Metadata-Version: 2.4
Name: bcra-connector
Version: 0.9.0
Summary: A Python connector for the BCRA (Banco Central de la República Argentina) APIs
Project-URL: Homepage, https://github.com/PPeitsch/bcra-connector
Project-URL: Documentation, https://bcra-connector.readthedocs.io/
Project-URL: Repository, https://github.com/PPeitsch/bcra-connector.git
Project-URL: Bug Tracker, https://github.com/PPeitsch/bcra-connector/issues
Project-URL: Changelog, https://github.com/PPeitsch/bcra-connector/blob/main/CHANGELOG.md
Author-email: Pablo Peitsch <pablo.peitsch@gmail.com>
License: MIT License
License-File: LICENSE
Keywords: argentina-api,banco-central-argentina,bcra,bcra-api,central-bank,currency-exchange,dolar,economic-indicators,exchange-rates,financial-data,inflation,monetary-statistics,python-bcra,tipo-cambio
Classifier: Development Status :: 4 - Beta
Classifier: Environment :: Console
Classifier: Framework :: Pytest
Classifier: Intended Audience :: Developers
Classifier: Intended Audience :: Financial and Insurance Industry
Classifier: Intended Audience :: Information Technology
Classifier: License :: OSI Approved :: MIT License
Classifier: Natural Language :: English
Classifier: Natural Language :: Spanish
Classifier: Operating System :: OS Independent
Classifier: Programming Language :: Python :: 3
Classifier: Programming Language :: Python :: 3 :: Only
Classifier: Programming Language :: Python :: 3.9
Classifier: Programming Language :: Python :: 3.10
Classifier: Programming Language :: Python :: 3.11
Classifier: Topic :: Internet :: WWW/HTTP
Classifier: Topic :: Office/Business :: Financial
Classifier: Topic :: Office/Business :: Financial :: Investment
Classifier: Topic :: Software Development :: Libraries :: Application Frameworks
Classifier: Topic :: Software Development :: Libraries :: Python Modules
Classifier: Typing :: Typed
Requires-Python: >=3.9
Requires-Dist: numpy<1.27.0,~=1.26.4
Requires-Dist: requests<2.33.0,>=2.32.0
Requires-Dist: scipy<1.15.0,>=1.13.1
Requires-Dist: urllib3<3.0.0,>=2.2.1
Provides-Extra: dev
Requires-Dist: black>=23.0.0; extra == 'dev'
Requires-Dist: isort>=5.0.0; extra == 'dev'
Requires-Dist: matplotlib<3.8.0,>=3.7.3; extra == 'dev'
Requires-Dist: mypy>=1.0.0; extra == 'dev'
Requires-Dist: numpy>=1.26.4; extra == 'dev'
Requires-Dist: pandas>=1.5.0; extra == 'dev'
Requires-Dist: pytest-cov>=4.1.0; extra == 'dev'
Requires-Dist: pytest-timeout>=2.1.0; extra == 'dev'
Requires-Dist: pytest<8.0.0,>=6.0.0; extra == 'dev'
Requires-Dist: scipy>=1.13.1; extra == 'dev'
Requires-Dist: setuptools>=78.1.1; extra == 'dev'
Requires-Dist: sphinx<9.0.0,>=6.0.0; extra == 'dev'
Requires-Dist: twine>=5.1.1; extra == 'dev'
Requires-Dist: types-requests>=2.31.0; extra == 'dev'
Requires-Dist: types-urllib3>=1.26.0; extra == 'dev'
Provides-Extra: pandas
Requires-Dist: pandas>=1.5.0; extra == 'pandas'
